greenlight/__init__.py
greenlight/_greenlight_internal.py
greenlight/_user_interface.py
greenlight/core.py
greenlight/energy_plus.py
greenlight/main.py
greenlight/main_cli.py
greenlight/utils.py
greenlight/_load/__init__.py
greenlight/_load/_expand_functions.py
greenlight/_load/_parse_model.py
greenlight/_load/_utils.py
greenlight/_load/core.py
greenlight/_save/__init__.py
greenlight/_save/core.py
greenlight/_solve/__init__.py
greenlight/_solve/_solve_ivp.py
greenlight/_solve/_solve_ivp_from_str.py
greenlight/_solve/_solver.py
greenlight/_solve/core.py
greenlight/models/katzin_2021/readme.txt
greenlight/models/katzin_2021/definition/extension_greenhouse_katzin_2021_vanthoor_2011.json
greenlight/models/katzin_2021/definition/lamp_hps_katzin_2020.json
greenlight/models/katzin_2021/definition/lamp_hps_katzin_2021.json
greenlight/models/katzin_2021/definition/main_katzin_2020.json
greenlight/models/katzin_2021/definition/main_katzin_2021.json
greenlight/models/katzin_2021/definition/modification_katzin_2020_katzin_2021.json
greenlight/models/katzin_2021/definition/readme.txt
greenlight/models/katzin_2021/definition/vanthoor_2011/controls_katzin_2021.json
greenlight/models/katzin_2021/definition/vanthoor_2011/crop_vanthoor_2011_chapter_9_simplified.json
greenlight/models/katzin_2021/definition/vanthoor_2011/extension_crop_vanthoor_2011_for_standalone.json
greenlight/models/katzin_2021/definition/vanthoor_2011/greenhouse_vanthoor_2011_chapter_8.json
greenlight/models/katzin_2021/definition/vanthoor_2011/main_vanthoor_2011.json
greenlight/models/katzin_2021/definition/vanthoor_2011/main_vanthoor_crop.json
greenlight/models/katzin_2021/definition/vanthoor_2011/readme.txt
greenlight/models/katzin_2021/input_data/test_data/Bleiswijk_from_20091020.csv
greenlight/models/katzin_2021/input_data/test_data/Readme.txt
greenlight/models/van_henten_2003/readme.txt
greenlight/models/van_henten_2003/definition/control_setpoints.json
greenlight-2.0.5.dist-info/licenses/LICENSE.txt
greenlight-2.0.5.dist-info/METADATA
greenlight-2.0.5.dist-info/WHEEL
greenlight-2.0.5.dist-info/top_level.txt
greenlight-2.0.5.dist-info/RECORD
