Metadata-Version: 2.4
Name: GreenLight
Version: 2.0.5
Summary: A platform for creating, modifying, and combining dynamic models, with a focus on horticultural greenhouses and crops
Home-page: https://github.com/davkat1/GreenLight
Author: David Katzin
Author-email: David Katzin <david.katzin@wur.nl>
License-Expression: BSD-3-Clause-Clear
Keywords: greenlight,greenhouse,crop,modelling
Requires-Python: >3.9
License-File: LICENSE.txt
Requires-Dist: numpy~=1.26.4
Requires-Dist: numexpr~=2.10.1
Requires-Dist: scipy~=1.14.1
Requires-Dist: pandas~=2.2.3
Requires-Dist: matplotlib~=3.10.0
Requires-Dist: tkcalendar~=1.6.1
Provides-Extra: dev
Requires-Dist: flake8; extra == "dev"
Requires-Dist: jupyter; extra == "dev"
Requires-Dist: jupytext; extra == "dev"
Requires-Dist: pre-commit; extra == "dev"
Requires-Dist: black; extra == "dev"
Requires-Dist: isort; extra == "dev"
Requires-Dist: setuptools; extra == "dev"
Requires-Dist: twine; extra == "dev"
Requires-Dist: build; extra == "dev"
Dynamic: author
Dynamic: home-page
Dynamic: license-file
